[
  {
    "DisplayName": "Đơn vị vận chuyển (Views)",
    "Name": "_crdfd_onvivanchuyen_views",
    "RelatedEntityName": "Đơn vị vận chuyển",
    "TrimmedViewName": true,
    "Type": "ViewInfo",
    "ViewInfoNameMapping": {
      "0301e432-3358-ee11-be6f-6045bd1e436a": "Đơn vị vận chuyển - Nhập",
      "11692f81-3b25-ef11-840b-6045bd1c25d6": "Chành xe",
      "52130bc9-d6f7-4fbc-8f8f-2d0305b071a1": "Đơn vị vận chuyển Associated View",
      "61fa7cc5-ade8-44a7-bcda-ba9b1eb34c5e": "Inactive Đơn vị vận chuyển",
      "63739688-65bc-4d02-a46c-03bd333b27f5": "Đơn vị vận chuyển Advanced Find View",
      "8357eacb-753c-48d3-86ee-84d5262f8918": "Đơn vị vận chuyển Lookup View",
      "bc01dfa4-3b25-ef11-840b-000d3aa1da25": "Nhà xe",
      "c470f168-da53-4c9c-85a1-31cc6c4e266f": "Đơn vị vận chuyển",
      "de3cef8b-485b-ee11-8def-6045bd1f9e5b": "Đơn vị vận chuyển - Xuất"
    }
  },
  {
    "DisplayName": "Ngày chạy trong tuần (Đơn vị vận chuyển)",
    "Name": "cr1bb_crdfd_onvivanchuyen_cr1bb_ngaychaytrongtuan",
    "OptionSetInfoNameMapping": {
      "283640000": "1",
      "283640001": "2",
      "283640002": "3",
      "283640003": "4",
      "283640004": "5",
      "283640005": "6",
      "283640006": "7"
    },
    "OptionSetIsBooleanValued": false,
    "OptionSetIsGlobal": false,
    "OptionSetReference": {
      "OptionSetReferenceItem0": {
        "OptionSetReferenceColumnName": "cr1bb_ngaychaytrongtuan",
        "OptionSetReferenceEntityName": "Đơn vị vận chuyển"
      }
    },
    "OptionSetTypeKey": "MultiSelectPicklistType",
    "RelatedColumnInvariantName": "cr1bb_ngaychaytrongtuan",
    "RelatedEntityName": "Đơn vị vận chuyển",
    "Type": "OptionSetInfo"
  },
  {
    "DisplayName": "Tần suất (Đơn vị vận chuyển)",
    "Name": "cr1bb_crdfd_onvivanchuyen_cr1bb_tansuat",
    "OptionSetInfoNameMapping": {
      "283640000": "Daily",
      "283640001": "Custom"
    },
    "OptionSetIsBooleanValued": false,
    "OptionSetIsGlobal": false,
    "OptionSetReference": {
      "OptionSetReferenceItem0": {
        "OptionSetReferenceColumnName": "cr1bb_tansuat",
        "OptionSetReferenceEntityName": "Đơn vị vận chuyển"
      }
    },
    "OptionSetTypeKey": "PicklistType",
    "RelatedColumnInvariantName": "cr1bb_tansuat",
    "RelatedEntityName": "Đơn vị vận chuyển",
    "Type": "OptionSetInfo"
  },
  {
    "DisplayName": "Nhập/Xuất (Đơn vị vận chuyển)",
    "Name": "crdfd_onvivanchuyen_crdfd_nhapxuat",
    "OptionSetInfoNameMapping": {
      "191920000": "Nhập",
      "191920001": "Xuất"
    },
    "OptionSetIsBooleanValued": false,
    "OptionSetIsGlobal": false,
    "OptionSetReference": {
      "OptionSetReferenceItem0": {
        "OptionSetReferenceColumnName": "crdfd_nhapxuat",
        "OptionSetReferenceEntityName": "Đơn vị vận chuyển"
      }
    },
    "OptionSetTypeKey": "PicklistType",
    "RelatedColumnInvariantName": "crdfd_nhapxuat",
    "RelatedEntityName": "Đơn vị vận chuyển",
    "Type": "OptionSetInfo"
  },
  {
    "DisplayName": "Phân loại (Đơn vị vận chuyển)",
    "Name": "crdfd_onvivanchuyen_crdfd_phanloai",
    "OptionSetInfoNameMapping": {
      "191920000": "Chành xe",
      "191920001": "Nhà xe",
      "191920002": "Trung chuyển (kho)"
    },
    "OptionSetIsBooleanValued": false,
    "OptionSetIsGlobal": false,
    "OptionSetReference": {
      "OptionSetReferenceItem0": {
        "OptionSetReferenceColumnName": "crdfd_phanloai",
        "OptionSetReferenceEntityName": "Đơn vị vận chuyển"
      }
    },
    "OptionSetTypeKey": "PicklistType",
    "RelatedColumnInvariantName": "crdfd_phanloai",
    "RelatedEntityName": "Đơn vị vận chuyển",
    "Type": "OptionSetInfo"
  },
  {
    "DisplayName": "Status (Đơn vị vận chuyển)",
    "Name": "crdfd_onvivanchuyen_statecode",
    "OptionSetInfoNameMapping": {
      "0": "Active",
      "1": "Inactive"
    },
    "OptionSetIsBooleanValued": false,
    "OptionSetIsGlobal": false,
    "OptionSetReference": {
      "OptionSetReferenceItem0": {
        "OptionSetReferenceColumnName": "statecode",
        "OptionSetReferenceEntityName": "Đơn vị vận chuyển"
      }
    },
    "OptionSetTypeKey": "StateType",
    "RelatedColumnInvariantName": "statecode",
    "RelatedEntityName": "Đơn vị vận chuyển",
    "Type": "OptionSetInfo"
  },
  {
    "DisplayName": "Status Reason (Đơn vị vận chuyển)",
    "Name": "crdfd_onvivanchuyen_statuscode",
    "OptionSetInfoNameMapping": {
      "1": "Active",
      "2": "Inactive"
    },
    "OptionSetIsBooleanValued": false,
    "OptionSetIsGlobal": false,
    "OptionSetReference": {
      "OptionSetReferenceItem0": {
        "OptionSetReferenceColumnName": "statuscode",
        "OptionSetReferenceEntityName": "Đơn vị vận chuyển"
      }
    },
    "OptionSetTypeKey": "StatusType",
    "RelatedColumnInvariantName": "statuscode",
    "RelatedEntityName": "Đơn vị vận chuyển",
    "Type": "OptionSetInfo"
  },
  {
    "CdsFCBContext": "{\"FileType\":true,\"ImageExternalStorage\":true}",
    "EntitySetName": "crdfd_onvivanchuyens",
    "IsHidden": false,
    "IsSampleData": false,
    "IsWritable": true,
    "LogicalName": "crdfd_onvivanchuyen",
    "MaxGetRowsCount": 2000,
    "Name": "Đơn vị vận chuyển",
    "NativeCDSDataSourceInfoNameMapping": {
      "_ownerid_value": "Owner",
      "{Attachments}": "Attachments",
      "cr1bb_crdfd_athangbo_VVC_crdfd_onvivanchuyen": "Đặt hàng BO",
      "cr1bb_crdfd_buyorders_donvivanchuyenquocte_crdfd_onvivanchuyen": "BuyOrders (cr1bb_crdfd_buyorders_donvivanchuyenquocte_crdfd_onvivanchuyen)",
      "cr1bb_crdfd_kehoachhangve_draft_onvivanchuyen_crdfd_onvivanchuyen": "Kế hoạch hàng về",
      "cr1bb_crdfd_transactionsales_onvivanchuyen_crdf": "Transaction Sales",
      "cr1bb_kehoachvantai_Xeexuat_crdfd_onvivanchuyen": "Kế hoạch vận tảis",
      "cr1bb_ngaychaytrongtuan": "Ngày chạy trong tuần",
      "cr1bb_Nhaxe_crdfd_onvivanchuyen": "Phiếu nhận hàngs",
      "cr1bb_note": "Note",
      "cr1bb_tansuat": "Tần suất",
      "cr1bb_thoigian": "Thời gian( 0h - 23h)",
      "cr1bb_Tuyengiaohang": "Tuyến giao hàng",
      "cr1bb_tuyenxonvivanchuyen_onvivanchuyen_crdfd_onvivanchuyen": "Tuyến x Đơn vị vận chuyểns",
      "cr1bb_Vitrikho": "Vị trí kho",
      "crdfd_Chanhxe": "Chành xe",
      "crdfd_cr1bb_giaobuhangsailech_Chanhxe_crdfd_onvivanchuyen": "Giao bù hàng sai lệches",
      "crdfd_cr1bb_tuyenxkhachhang_onvivanchuyen_crdfd_onvivanchuyen": "Tuyến x khách hàngs",
      "crdfd_crdfd_buyorders_onvivanchuyen_crdfd_onviv": "BuyOrders (crdfd_crdfd_buyorders_onvivanchuyen_crdfd_onviv)",
      "crdfd_crdfd_phieunhapkho_Nhaxe_crdfd_onvivanchu": "Phiếu nhập kho",
      "crdfd_crdfd_saleorderdetail_DHgaponvivanchuyen_": "Sale Order Details",
      "crdfd_crdfd_transactionbuy_onvivanchuyennew_crd": "Transaction Buys",
      "crdfd_customer_Nhaxe_crdfd_onvivanchuyen": "Customers",
      "crdfd_customerxvantai_onvivanchuyen_crdfd_onvivanchuyen": "Customer x Vận tải",
      "crdfd_dvvc_auto": "DVVC_auto",
      "crdfd_hangduloichuanhapkho_Nhaxe_crdfd_onvivanchuyen": "Hàng dư lỗi chưa nhập khos",
      "crdfd_name": "Đơn vị vận chuyển (crdfd_name)",
      "crdfd_nguoilienhe": "Người liên hệ",
      "crdfd_nhapxuat": "Nhập/Xuất",
      "crdfd_onvivanchuyen_ActivityPointers": "Activities",
      "crdfd_onvivanchuyen_adx_alertsubscriptions": "Alert Subscriptions",
      "crdfd_onvivanchuyen_adx_inviteredemptions": "Invite Redemptions",
      "crdfd_onvivanchuyen_adx_portalcomments": "Portal Comments",
      "crdfd_onvivanchuyen_Annotations": "Notes",
      "crdfd_onvivanchuyen_Appointments": "Appointments",
      "crdfd_onvivanchuyen_AsyncOperations": "System Jobs",
      "crdfd_onvivanchuyen_BulkDeleteFailures": "Bulk Delete Failures",
      "crdfd_onvivanchuyen_Chanhxe_crdfd_onvivanchuyen": "Đơn vị vận chuyển (crdfd_onvivanchuyen_Chanhxe_crdfd_onvivanchuyen)",
      "crdfd_onvivanchuyen_chats": "Teams chats",
      "crdfd_onvivanchuyen_DuplicateBaseRecord": "Duplicate Records (crdfd_onvivanchuyen_DuplicateBaseRecord)",
      "crdfd_onvivanchuyen_DuplicateMatchingRecord": "Duplicate Records (crdfd_onvivanchuyen_DuplicateMatchingRecord)",
      "crdfd_onvivanchuyen_Emails": "Email Messages",
      "crdfd_onvivanchuyen_Faxes": "Faxes",
      "crdfd_onvivanchuyen_Letters": "Letters",
      "crdfd_onvivanchuyen_MailboxTrackingFolders": "Mailbox Auto Tracking Folders",
      "crdfd_onvivanchuyen_msfp_alerts": "Customer Voice alert",
      "crdfd_onvivanchuyen_msfp_surveyinvites": "Customer Voice survey invites",
      "crdfd_onvivanchuyen_msfp_surveyresponses": "Customer Voice survey responses",
      "crdfd_onvivanchuyen_PhoneCalls": "Phone Calls",
      "crdfd_onvivanchuyen_PrincipalObjectAttributeAccesses": "Field Sharing",
      "crdfd_onvivanchuyen_ProcessSession": "Process Sessions",
      "crdfd_onvivanchuyen_RecurringAppointmentMasters": "Recurring Appointments",
      "crdfd_onvivanchuyen_SyncErrors": "Sync Errors",
      "crdfd_onvivanchuyen_Tasks": "Tasks",
      "crdfd_onvivanchuyenid": "ID",
      "crdfd_onvivanchuyenxcustomer_onvivanchuyen_crdfd_onvivanchuyen": "Đơn vị vận chuyển x Customers",
      "crdfd_phanloai": "Phân loại",
      "crdfd_phone": "Số điện thoại",
      "crdfd_quality_donvivanchuyen_crdfd_onvivanchuyen": "Qualities",
      "crdfd_supplier_Chanhxevanchuyen_crdfd_onvivanch": "Suppliers",
      "crdfd_thoigian": "Thời gian text",
      "crdfd_Tuyen_giao_hang": "Tỉnh/thành",
      "crdfd_vantai_Chanh_xe_crdfd_onvivanchuyen": "Vận tải (crdfd_vantai_Chanh_xe_crdfd_onvivanchuyen)",
      "crdfd_vantai_Nhaxe_crdfd_onvivanchuyen": "Vận tải (crdfd_vantai_Nhaxe_crdfd_onvivanchuyen)",
      "createdby": "Created By",
      "createdon": "Created On",
      "createdonbehalfby": "Created By (Delegate)",
      "importsequencenumber": "Import Sequence Number",
      "modifiedby": "Modified By",
      "modifiedon": "Modified On",
      "modifiedonbehalfby": "Modified By (Delegate)",
      "overriddencreatedon": "Record Created On",
      "owningbusinessunit": "Owning Business Unit",
      "owningteam": "Owning Team",
      "owninguser": "Owning User",
      "statecode": "Status",
      "statuscode": "Status Reason",
      "timezoneruleversionnumber": "Time Zone Rule Version Number",
      "utcconversiontimezonecode": "UTC Conversion Time Zone Code",
      "versionnumber": "Version Number"
    },
    "PreferredName": "Đơn vị vận chuyển",
    "Type": "NativeCDSDataSourceInfo"
  }
]